[{"value":"uphurls","paths":{"2":{"c":2,"f":1}},"prevalence":"0","glossary":null},{"value":"upfurls","paths":{"1":{"n":4},"2":{"c":2,"h":0}},"prevalence":"0","glossary":null},{"value":"upcurls","paths":{"1":{"n":3},"2":{"f":1,"h":0}},"prevalence":"6.0692842184917","glossary":null},{"value":"uncurls","paths":{"5":{"b":5},"2":{"f":4},"1":{"p":2}},"prevalence":"166.34641860821","glossary":null},{"value":"unfurls","paths":{"2":{"c":3},"1":{"p":1}},"prevalence":"1079.5614110005","glossary":null},{"value":"uncurbs","paths":{"5":{"l":3}},"prevalence":"0","glossary":null}]