[{"value":"economizes","paths":{"7":{"s":4},"9":{"d":2,"r":1}},"prevalence":"511.35295679417","glossary":null},{"value":"economizer","paths":{"7":{"s":7},"9":{"d":2,"s":0}},"prevalence":"437.34740246945","glossary":"a frugal person who limits spending and avoids waste"},{"value":"economized","paths":{"7":{"s":3},"9":{"r":1,"s":0}},"prevalence":"1270.5532587011","glossary":null},{"value":"economised","paths":{"9":{"r":7,"s":4},"7":{"z":2}},"prevalence":"537.77359258973","glossary":null},{"value":"economises","paths":{"9":{"d":3,"r":7},"8":{"m":6,"t":5},"7":{"z":0}},"prevalence":"185.3171450596","glossary":null},{"value":"economists","paths":{"8":{"e":4,"m":6}},"prevalence":"44924.282672412","glossary":null},{"value":"economisms","paths":{"8":{"e":4,"t":5}},"prevalence":"3.4369161693554","glossary":null},{"value":"economiser","paths":{"9":{"d":3,"s":4},"7":{"z":1}},"prevalence":"116.24685369748","glossary":"a frugal person who limits spending and avoids waste"}]