[{"value":"theologize","paths":{"8":{"s":1}},"prevalence":"224.83511363892","glossary":"make theoretical speculations about theology or discuss theological subjects"},{"value":"theologise","paths":{"9":{"t":2},"8":{"z":0}},"prevalence":"35.194583029185","glossary":"make theoretical speculations about theology or discuss theological subjects"},{"value":"theologist","paths":{"0":{"r":3},"9":{"e":1}},"prevalence":"193.79892163992","glossary":"someone who is learned in theology or who speculates about theology (especially Christian theology)"},{"value":"rheologist","paths":[{"t":2}],"prevalence":"9.9536394812061","glossary":null}]