[{"value":"systemizes","paths":{"7":{"s":4},"9":{"d":2,"r":1}},"prevalence":"28.814104704023","glossary":null},{"value":"systemizer","paths":{"7":{"s":5},"9":{"d":2,"s":0}},"prevalence":"22.912064404455","glossary":"an organizer who puts things in order; \"Aristotle was a great orderer of ideas\""},{"value":"systemized","paths":{"7":{"s":3},"9":{"r":1,"s":0}},"prevalence":"545.35580662366","glossary":null},{"value":"systemised","paths":{"9":{"r":5,"s":4},"7":{"z":2}},"prevalence":"107.88527722035","glossary":null},{"value":"systemises","paths":{"9":{"d":3,"r":5},"7":{"z":0}},"prevalence":"7.8473847417027","glossary":null},{"value":"systemiser","paths":{"9":{"d":3,"s":4},"7":{"z":1}},"prevalence":"3.2522262788856","glossary":"an organizer who puts things in order; \"Aristotle was a great orderer of ideas\""}]