[{"value":"revolving","paths":{"0":{"d":3},"2":{"s":2},"5":{"t":1}},"prevalence":"36015.009679225","glossary":null},{"value":"revolting","paths":{"5":{"v":0}},"prevalence":"17757.823298965","glossary":"highly offensive; arousing aversion or disgust; \"a disgusting smell\"; \"distasteful language\"; \"a loathsome disease\"; \"the idea of eating meat is repellent to me\"; \"revolting food\"; \"a wicked stench\""},{"value":"resolving","paths":{"2":{"v":0}},"prevalence":"52238.592699758","glossary":"analysis into clear-cut components"},{"value":"devolving","paths":[{"r":0}],"prevalence":"3592.0594032021","glossary":null}]