[{"value":"retouring","paths":{"0":{"d":4},"2":{"c":2,"p":1}},"prevalence":"0.50643956661224","glossary":null},{"value":"repouring","paths":{"2":{"c":2,"t":0}},"prevalence":"13.877398268961","glossary":null},{"value":"recouring","paths":{"5":{"p":3},"2":{"p":1,"t":0}},"prevalence":"0","glossary":null},{"value":"recouping","paths":{"5":{"r":2}},"prevalence":"1338.8934221592","glossary":null},{"value":"detouring","paths":{"2":{"v":5},"0":{"r":0}},"prevalence":"576.52077751004","glossary":null},{"value":"devouring","paths":{"2":{"t":4}},"prevalence":"22756.052511856","glossary":null}]