[{"value":"radialize","paths":{"2":{"c":3},"7":{"s":1}},"prevalence":"0","glossary":null},{"value":"radialise","paths":{"2":{"c":2},"7":{"z":0}},"prevalence":"0","glossary":null},{"value":"racialise","paths":{"8":{"m":5,"t":4},"7":{"z":3},"2":{"d":1}},"prevalence":"40.692209222839","glossary":null},{"value":"racialize","paths":{"7":{"s":2},"2":{"d":0}},"prevalence":"325.06668495896","glossary":null},{"value":"racialist","paths":{"8":{"e":2,"m":5}},"prevalence":"1587.3981538398","glossary":"a person with a prejudiced belief that one race is superior to others"},{"value":"racialism","paths":{"8":{"e":2,"t":4}},"prevalence":"1668.4535437136","glossary":"discriminatory or abusive behavior towards members of another race"}]