[{"value":"printless","paths":{"1":{"o":1}},"prevalence":"125.50802085132","glossary":null},{"value":"pointless","paths":[{"j":2},{"r":0}],"prevalence":"25298.633010998","glossary":"lacking import; \"a pointless remark\"; \"a life essentially purposeless\"; \"senseless violence\""},{"value":"jointless","paths":{"5":{"n":4,"r":3},"0":{"p":1}},"prevalence":"208.57799141258","glossary":null},{"value":"jointress","paths":{"5":{"l":2,"n":4}},"prevalence":"51.096515374484","glossary":null},{"value":"jointness","paths":{"5":{"l":2,"r":3}},"prevalence":"536.653855944","glossary":null}]