[{"value":"voracious","paths":{"1":{"e":1}},"prevalence":"12025.567275051","glossary":"devouring or craving food in great quantities; \"edacious vultures\"; \"a rapacious appetite\"; \"ravenous as wolves\"; \"voracious sharks\""},{"value":"veracious","paths":[{"f":2},{"o":0}],"prevalence":"2603.7939077583","glossary":"precisely accurate; \"a veracious account\""},{"value":"feracious","paths":{"3":{"o":5},"1":{"u":3},"0":{"v":1}},"prevalence":"13.748775566618","glossary":null},{"value":"furacious","paths":{"1":{"e":2},"2":{"g":4}},"prevalence":"3.9340938735754","glossary":null},{"value":"fugacious","paths":{"2":{"r":3}},"prevalence":"276.18522987041","glossary":"enduring a very short time; \"the ephemeral joys of childhood\"; \"a passing fancy\"; \"youth''s transient beauty\"; \"love is transitory but at is eternal\"; \"fugacious blossoms\""},{"value":"ferocious","paths":{"3":{"a":2}},"prevalence":"33397.110076183","glossary":"marked by extreme and violent energy; \"a ferocious beating\"; \"fierce fighting\"; \"a furious battle\""}]