[{"value":"leukaemia","paths":{"3":{"c":1}},"prevalence":"3692.9886170916","glossary":"malignant neoplasm of blood-forming tissues; characterized by abnormal proliferation of leukocytes; one of the four major types of cancer"},{"value":"leucaemia","paths":{"8":{"c":2},"3":{"k":0}},"prevalence":"20.37208543113","glossary":"malignant neoplasm of blood-forming tissues; characterized by abnormal proliferation of leukocytes; one of the four major types of cancer"},{"value":"leucaemic","paths":{"8":{"a":1}},"prevalence":"3.39283228512","glossary":null}]