[{"value":"harmonies","paths":{"2":{"e":3},"7":{"c":1}},"prevalence":"14868.900843122","glossary":null},{"value":"harmonics","paths":{"8":{"a":2},"7":{"e":0}},"prevalence":"8136.0292152628","glossary":"the study of musical sound"},{"value":"harmonica","paths":{"8":{"s":1}},"prevalence":"3878.9529028045","glossary":"a small rectangular free-reed instrument having a row of free reeds set back in air holes and played by blowing into the desired hole"},{"value":"haemonies","paths":{"2":{"r":0}},"prevalence":"0","glossary":null}]