[{"value":"synergize","paths":{"7":{"s":1}},"prevalence":"632.02897499198","glossary":null},{"value":"synergise","paths":{"8":{"m":3,"t":2},"7":{"z":0}},"prevalence":"98.188542222419","glossary":null},{"value":"synergist","paths":{"8":{"e":1,"m":3}},"prevalence":"301.16331717291","glossary":"a drug that augments the activity of another drug"},{"value":"synergism","paths":{"8":{"e":1,"t":2}},"prevalence":"2052.716700262","glossary":"the theological doctrine that salvation results from the interaction of human will and divine grace"}]