[{"value":"subtunic","paths":{"4":{"o":1}},"prevalence":"0","glossary":null},{"value":"subtonic","paths":{"3":{"s":4},"5":{"p":2},"4":{"u":0}},"prevalence":"75.148909346844","glossary":"(music) the seventh note of the diatonic scale"},{"value":"subtopic","paths":{"5":{"n":1},"7":{"a":3}},"prevalence":"812.12618584419","glossary":null},{"value":"subtopia","paths":{"7":{"c":2}},"prevalence":"14.656711946196","glossary":"monotonous urban sprawl of standardized buildings"},{"value":"subsonic","paths":{"3":{"t":1}},"prevalence":"1466.0974321051","glossary":"(of speed) less than that of sound in a designated medium; \"aircraft flying at subsonic speeds\""}]