[{"value":"sabulous","paths":[{"f":5,"p":1}],"prevalence":"26.373305339491","glossary":null},{"value":"pabulous","paths":{"0":{"f":5,"s":0},"2":{"p":3,"t":2}},"prevalence":"0.36901884159064","glossary":null},{"value":"patulous","paths":{"2":{"b":1,"p":3}},"prevalence":"289.18101766444","glossary":null},{"value":"papulous","paths":{"2":{"b":1,"t":2},"1":{"o":4}},"prevalence":"33.931584421421","glossary":null},{"value":"populous","paths":{"1":{"a":3}},"prevalence":"24884.500507966","glossary":"densely populated"},{"value":"fabulous","paths":[{"p":1,"s":0}],"prevalence":"38095.88905648","glossary":"barely credible; \"the fabulous endurance of a marathon runner\""}]