[{"value":"recurves","paths":{"0":{"d":4},"7":{"d":1}},"prevalence":"93.148383391495","glossary":null},{"value":"recurved","paths":{"0":{"d":3},"5":{"r":2},"7":{"s":0}},"prevalence":"1084.2226062221","glossary":"curved backward or inward"},{"value":"recurred","paths":{"5":{"v":1}},"prevalence":"10667.567419502","glossary":null},{"value":"decurved","paths":{"7":{"s":4},"0":{"r":1}},"prevalence":"125.6883032698","glossary":"bent down or curved downward; \"the decurved bill of a curlew\""},{"value":"decurves","paths":{"5":{"i":5},"7":{"d":3},"0":{"r":0}},"prevalence":"2.8257227540016","glossary":null},{"value":"decuries","paths":{"6":{"a":6},"5":{"v":4}},"prevalence":"55.471852778739","glossary":null},{"value":"decurias","paths":{"6":{"e":5}},"prevalence":"8.4298207459138","glossary":null}]