[{"value":"minimize","paths":{"6":{"s":1}},"prevalence":"86539.607672513","glossary":"make small or insignificant; \"Let''s minimize the risk\""},{"value":"minimise","paths":{"7":{"m":3,"t":2},"6":{"z":0}},"prevalence":"14083.309381703","glossary":"make small or insignificant; \"Let''s minimize the risk\""},{"value":"minimist","paths":{"7":{"e":1,"m":3}},"prevalence":"1.4799224297488","glossary":null},{"value":"minimism","paths":{"7":{"e":1,"t":2}},"prevalence":"3.6563756719563","glossary":null}]