[{"value":"loamiest","paths":[{"f":1}],"prevalence":"0","glossary":null},{"value":"foamiest","paths":{"1":{"l":2},"0":{"l":0}},"prevalence":"10.773956740721","glossary":null},{"value":"flamiest","paths":{"3":{"k":12,"r":5,"w":4,"x":3},"1":{"o":1}},"prevalence":"0","glossary":null},{"value":"flaxiest","paths":{"3":{"k":12,"m":2,"r":5,"w":4}},"prevalence":"0","glossary":null},{"value":"flawiest","paths":{"3":{"k":12,"m":2,"r":5,"x":3}},"prevalence":"0","glossary":null},{"value":"flariest","paths":{"3":{"k":12,"m":2,"w":4,"x":3},"2":{"o":11},"0":{"g":6}},"prevalence":"0","glossary":null},{"value":"glariest","paths":{"0":{"f":5},"3":{"d":8,"z":7}},"prevalence":"0","glossary":null},{"value":"glaziest","paths":{"3":{"d":8,"r":6}},"prevalence":"0","glossary":null},{"value":"gladiest","paths":{"4":{"d":9},"3":{"r":6,"z":7}},"prevalence":"0","glossary":null},{"value":"gladdest","paths":{"4":{"i":8},"2":{"i":10}},"prevalence":"616.53215605389","glossary":null},{"value":"gliddest","paths":{"2":{"a":9}},"prevalence":"0","glossary":null},{"value":"floriest","paths":{"2":{"a":5}},"prevalence":"0","glossary":null},{"value":"flakiest","paths":{"3":{"m":2,"r":5,"w":4,"x":3},"2":{"u":13}},"prevalence":"53.608895529665","glossary":null},{"value":"flukiest","paths":{"2":{"a":12},"3":{"t":14}},"prevalence":"9.3574657256093","glossary":null},{"value":"flutiest","paths":{"3":{"k":13}},"prevalence":"3.7884728379449","glossary":null}]