[{"value":"xenon","paths":[{"t":1}],"prevalence":"2592.1104625327","glossary":"a colorless odorless inert gaseous element occurring in the earth''s atmosphere in trace amounts"},{"value":"tenon","paths":{"4":{"r":2},"0":{"x":0}},"prevalence":"1917.73016992","glossary":"a projection at the end of a piece of wood that is shaped to fit into a mortise and form a mortise joint"},{"value":"tenor","paths":{"0":{"s":3},"4":{"n":1}},"prevalence":"38362.220429974","glossary":"the pitch range of the highest male voice"},{"value":"senor","paths":[{"t":2}],"prevalence":"3881.0816349845","glossary":"a Spanish title of respect for a man; equivalent to English `Mr''"}]