[{"value":"countercharmed","paths":{"11":{"g":1}},"prevalence":"0","glossary":null},{"value":"countercharged","paths":{"10":{"n":4},"13":{"s":2},"11":{"m":0}},"prevalence":"100.3261710059","glossary":null},{"value":"countercharges","paths":{"10":{"n":3},"13":{"d":1}},"prevalence":"774.97958396365","glossary":null},{"value":"counterchanges","paths":{"13":{"d":4},"10":{"r":2}},"prevalence":"11.559574402913","glossary":null},{"value":"counterchanged","paths":{"13":{"s":3},"10":{"r":1}},"prevalence":"94.440879213887","glossary":null}]