[{"value":"leishmaniosis","paths":{"9":{"a":3},"11":{"e":1}},"prevalence":"32.115650646097","glossary":"sores resulting from a tropical infection by protozoa of the genus Leishmania which are spread by sandflies"},{"value":"leishmanioses","paths":{"9":{"a":2},"11":{"i":0}},"prevalence":"4.0560382499707","glossary":null},{"value":"leishmaniases","paths":{"11":{"i":3},"9":{"o":1}},"prevalence":"22.704783947043","glossary":null},{"value":"leishmaniasis","paths":{"11":{"e":2},"9":{"o":0}},"prevalence":"1202.7617509967","glossary":"sores resulting from a tropical infection by protozoa of the genus Leishmania which are spread by sandflies"}]