[{"value":"parasitosis","paths":{"9":{"e":1}},"prevalence":"175.60332507397","glossary":null},{"value":"parasitoses","paths":{"7":{"i":2},"9":{"i":0}},"prevalence":"28.795038402991","glossary":null},{"value":"parasitises","paths":{"10":{"d":5},"9":{"m":6},"8":{"z":3},"7":{"o":1}},"prevalence":"29.136047399498","glossary":null},{"value":"parasitizes","paths":{"8":{"s":2},"10":{"d":4}},"prevalence":"212.30253805687","glossary":null},{"value":"parasitized","paths":{"8":{"s":5},"10":{"s":3}},"prevalence":"960.0978087606","glossary":null},{"value":"parasitised","paths":{"10":{"s":2},"8":{"z":4}},"prevalence":"164.46307412588","glossary":null},{"value":"parasitisms","paths":{"9":{"e":2}},"prevalence":"20.880495770086","glossary":null}]