[{"value":"orientalize","paths":{"9":{"s":1}},"prevalence":"62.621650321614","glossary":"make oriental in character; \"orientalize your garden\""},{"value":"orientalise","paths":{"10":{"m":3,"t":2},"9":{"z":0}},"prevalence":"16.119071911279","glossary":"make oriental in character; \"orientalize your garden\""},{"value":"orientalist","paths":{"10":{"e":1,"m":3}},"prevalence":"2758.6980547066","glossary":"a specialist in oriental subjects"},{"value":"orientalism","paths":{"10":{"e":1,"t":2}},"prevalence":"2367.4401557006","glossary":"the quality or customs or mannerisms characteristic of Asian civilizations; \"orientalisms can be found in Mozart''s operas\""}]