[{"value":"repopulates","paths":{"0":{"d":3},"10":{"d":1}},"prevalence":"54.284256869243","glossary":null},{"value":"repopulated","paths":{"0":{"d":2},"10":{"s":0}},"prevalence":"904.66618709447","glossary":null},{"value":"depopulated","paths":{"10":{"s":3},"0":{"r":1}},"prevalence":"5029.2775742315","glossary":"having lost inhabitants as by war or disease; \"the 15th century plagues left vast areas of Europe depopulated\""},{"value":"depopulates","paths":{"10":{"d":2},"0":{"r":0}},"prevalence":"120.73563546775","glossary":null}]